security_slackbot/__init__.py
security_slackbot/__main__.py
security_slackbot/cli.py
security_slackbot-0.1.0.dist-info/DESCRIPTION.rst
security_slackbot-0.1.0.dist-info/METADATA
security_slackbot-0.1.0.dist-info/RECORD
security_slackbot-0.1.0.dist-info/WHEEL
security_slackbot-0.1.0.dist-info/entry_points.txt
security_slackbot-0.1.0.dist-info/metadata.json
security_slackbot-0.1.0.dist-info/top_level.txt
